MANIFEST.in
changelog.rst
credits.txt
jsonrpcbase.py
readme.rst
setup.py
JSONRPCBase.egg-info/PKG-INFO
JSONRPCBase.egg-info/SOURCES.txt
JSONRPCBase.egg-info/dependency_links.txt
JSONRPCBase.egg-info/not-zip-safe
JSONRPCBase.egg-info/requires.txt
JSONRPCBase.egg-info/top_level.txt