Metadata-Version: 1.1
Name: JSONRPCBase
Version: 0.2.0
Summary: Simple JSON-RPC service without transport layer
Home-page: https://github.com/level12/jsonrpcbase
Author: Randy Syring
Author-email: randy.syring@level12.io
License: MIT
Platform: UNKNOWN
Classifier: Development Status :: 4 - Beta
Classifier: Intended Audience :: Developers
Classifier: License :: OSI Approved :: MIT License
Classifier: Operating System :: POSIX :: Linux
Classifier: Operating System :: Microsoft :: Windows
Classifier: Programming Language :: Python :: 2.7
Classifier: Programming Language :: Python :: 3.4
Classifier: Programming Language :: Python :: 3.5
